LICENSE
README.md
pyproject.toml
setup.cfg
setup.py
src/fast_link_extractor/__init__.py
src/fast_link_extractor/fast_link_extractor.py
src/fast_link_extractor.egg-info/PKG-INFO
src/fast_link_extractor.egg-info/SOURCES.txt
src/fast_link_extractor.egg-info/dependency_links.txt
src/fast_link_extractor.egg-info/not-zip-safe
src/fast_link_extractor.egg-info/requires.txt
src/fast_link_extractor.egg-info/top_level.txt