Metadata-Version: 2.1
Name: fast-link-extractor
Version: 0.1.0
Summary: quickly extract links from html
Home-page: https://github.com/lgloege/fast-link-extractor
Author: Luke Gloege
Author-email: ljg2157@columbia.edu
License: MIT
Keywords: html
Platform: unix
Platform: linux
Platform: osx
Platform: cygwin
Platform: win32
Classifier: Development Status :: 3 - Alpha
Classifier: Intended Audience :: Developers
Classifier: Topic :: Software Development :: Build Tools
Classifier: License :: OSI Approved :: MIT License
Classifier: Programming Language :: Python :: 3
Classifier: Programming Language :: Python :: 3 :: Only
Classifier: Programming Language :: Python :: 3.7
Classifier: Programming Language :: Python :: 3.8
Classifier: Programming Language :: Python :: 3.9
Requires-Python: >=3.7
Provides-Extra: testing
License-File: LICENSE
